summand/_import_.py
summand/app.json
summand/cli.py
summand/db.py
summand/export.py
summand/lists.json
summand/main.md
summand/utilities.py
summand-0.1.0.dist-info/entry_points.txt
summand-0.1.0.dist-info/WHEEL
summand-0.1.0.dist-info/METADATA
summand-0.1.0.dist-info/RECORD
